{"type": "Feature", "id": 12523337, "properties": {"woe:id": 12523337, "woe:parent_id": 57024, "woe:name": "Paradise Island Airport", "woe:placetype": 14, "woe:placetype_name": "Airport", "woe:lang": "ENG", "iso:country": "BS", "meta:provider": ["geoplanet:7.3.1", "geoplanet:7.3.2", "geoplanet:7.4.0", "geoplanet:7.4.1", "geoplanet:7.5.1", "geoplanet:7.5.2", "geoplanet:7.6.0", "geoplanet:7.8.1", "geoplanet:7.9.0", "geoplanet:7.10.0", "geoplanet:8.0.0", "woeplanet:8.0.0"], "meta:indexed": "2020-08-20T20:48:41.404275", "woe:alias_ENG_V": ["WZY Airport", "WZY", "Paradise Island Seaplane Base"], "meta:updated": "2020-08-22T01:55:47.937236", "woe:hierarchy": {"continent": 24865672, "country": 23424758, "town": 0, "planet": 1, "county": 0, "suburb": 0, "state": 2344777, "region": 0, "localadmin": 0}, "woe:timezone_id": 28350779, "woe:hash": "dk3n9hcw6kxx", "woe:centroid": [-77.297638, 25.076019], "geom:latitude": 25.076019, "geom:longitude": -77.297638, "geom:hash": "dk3n9hcw6kxx", "woe:latitude": 25.076019, "geom:centroid": [-77.297638, 25.076019], "woe:longitude": -77.297638, "woe:repo": "woeplanet-airport-bs"}, "geometry": {"coordinates": [-77.297638, 25.076019], "type": "Point"}}